url_util/__init__.py
url_util/url_util.py
url_util-0.1.2.dist-info/WHEEL
url_util-0.1.2.dist-info/METADATA
url_util-0.1.2.dist-info/RECORD
